xdownloader/__init__.py
xdownloader/main.py
xvideodownloader-0.1.0.dist-info/METADATA
xvideodownloader-0.1.0.dist-info/WHEEL
xvideodownloader-0.1.0.dist-info/top_level.txt
xvideodownloader-0.1.0.dist-info/RECORD
